menzalib/__init__.py
menzalib/analisi_errori.py
menzalib/errori_strumenti.py
menzalib/funzioni_fit.py
menzalib/latex.py
menzalib/test.py
menzalib-1.1.1.dist-info/LICENSE.txt
menzalib-1.1.1.dist-info/METADATA
menzalib-1.1.1.dist-info/WHEEL
menzalib-1.1.1.dist-info/top_level.txt
menzalib-1.1.1.dist-info/RECORD
