Metadata-Version: 2.1
Name: menzalib
Version: 1.1.1
Summary: Funzioni utili per lab3
Home-page: https://github.com/LetteraUnica/menzalib
Author: ['Lorenzo Cavuoti', 'Francesco Sacco']
Author-email: lorenzocav97@gmail.com
License: UNKNOWN
Platform: UNKNOWN
Classifier: Programming Language :: Python :: 3
Classifier: Operating System :: OS Independent
Requires-Dist: numpy
Requires-Dist: scipy
Requires-Dist: jax
